vek_parser/__init__.py
vek_parser/http_client.py
vek_parser/web_parser.py
vek_parser-0.1.7.dist-info/licenses/LICENSE
vek_parser-0.1.7.dist-info/METADATA
vek_parser-0.1.7.dist-info/WHEEL
vek_parser-0.1.7.dist-info/top_level.txt
vek_parser-0.1.7.dist-info/RECORD
