Metadata-Version: 2.4
Name: vek-parser
Version: 0.1.7
Summary: Универсальный парсер для сбора структурированных данных с веб-сайтов
Author: Emil Markov
Author-email: Emil Markov <markovemil2@gmail.com>
License: MIT
Project-URL: Homepage, https://github.com/EmilMarkov/VekParser
Project-URL: Repository, https://github.com/EmilMarkov/VekParser.git
Project-URL: Documentation, https://github.com/EmilMarkov/VekParser#readme
Keywords: web,parser,scraping,crawler
Classifier: Development Status :: 3 - Alpha
Classifier: Intended Audience :: Developers
Classifier: License :: OSI Approved :: MIT License
Classifier: Programming Language :: Python :: 3
Classifier: Programming Language :: Python :: 3.9
Classifier: Programming Language :: Python :: 3.10
Classifier: Programming Language :: Python :: 3.11
Classifier: Programming Language :: Python :: 3.12
Classifier: Programming Language :: Python :: 3.13
Requires-Python: >=3.9
License-File: LICENSE
Requires-Dist: requests>=2.32.3
Requires-Dist: selectorlib>=0.16.0
Requires-Dist: parsel>=1.7.0
Requires-Dist: PyYAML>=5.4.0
Requires-Dist: playwright~=1.50.0
Dynamic: license-file
